quboassist-0.0.19.dist-info/METADATA
quboassist-0.0.19.dist-info/WHEEL
quboassist-0.0.19.dist-info/entry_points.txt
quboassist-0.0.19.dist-info/licenses/LICENSE
quboassist/main.py
quboassist/__init__.py
quboassist/__pycache__/main.cpython-313.pyc
quboassist/__pycache__/__init__.cpython-313.pyc
quboassist/quboassistfunc.cp311-win_amd64.pyd
quboassist-0.0.19.dist-info/RECORD
