Metadata-Version: 2.3
Name: quboassist
Version: 0.0.19
Classifier: Programming Language :: Python :: 3
Classifier: Programming Language :: Rust
Classifier: License :: OSI Approved :: MIT License
Classifier: Operating System :: OS Independent
Requires-Dist: numpy
Requires-Dist: build ; extra == 'dev'
Requires-Dist: twine ; extra == 'dev'
Provides-Extra: dev
License-File: LICENSE
Summary: Generate QUBO which can be input to dwave-neal simulated annealing solver and reconstruct the solution of the original problem.
Keywords: QUBO,Simulated annealing
Author-email: Enomoto Kan <enomotokan@gmail.com>
Requires-Python: >=3.8
Project-URL: Homepage, https://github.com/enomotokan/quboassist
